setup.cfg
setup.py
lshca/__init__.py
lshca/cli.py
lshca/config.py
lshca/datasource.py
lshca/hca_manager.py
lshca/misc_cmds.py
lshca/mlx_hca.py
lshca/mst_device.py
lshca/pci_device.py
lshca/raw_mlnx_bdf_device.py
lshca/sa_smpquery_device.py
lshca/service_function.py
lshca/sysfs_device.py
lshca.egg-info/PKG-INFO
lshca.egg-info/SOURCES.txt
lshca.egg-info/dependency_links.txt
lshca.egg-info/entry_points.txt
lshca.egg-info/top_level.txt