Metadata-Version: 1.1
Name: lshca
Version: 4.0-rc1
Summary: This utility and library comes to provide bird's-eye view of HCAs installed
Home-page: https://github.com/MrBr-github/lshca
Author: Michael Braverman
Author-email: mrbr.mail@gmail.com
License: GNU GPLv3
Download-URL: https://github.com/MrBr-github/lshca/archive/v4.0.tar.gz
Keywords: HCA,INFINIBAND
Platform: UNKNOWN
Classifier: Development Status :: 3 - Alpha
Classifier: Intended Audience :: System Administrators
Classifier: Intended Audience :: Information Technology
Classifier: License :: OSI Approved :: GNU General Public License v3 (GPLv3)
Classifier: Programming Language :: Python :: 2.7
Classifier: Programming Language :: Python :: 3
